rin/docutils/__init__.py
rin/docutils/flag.py
rin/docutils/markers.py
rin/docutils/autodecorator/__init__.py
rin/docutils/autodecorator/_modified_generate_autosummary_content.py
rin/docutils/autodecorator/templates/autosummary/module.rst
rin_docutils-1.0.0.dist-info/LICENSE
rin_docutils-1.0.0.dist-info/METADATA
rin_docutils-1.0.0.dist-info/WHEEL
rin_docutils-1.0.0.dist-info/top_level.txt
rin_docutils-1.0.0.dist-info/RECORD
